materia/.gitignore
materia/__init__.py
materia/actions/__init__.py
materia/actions/action.py
materia/actions/core.py
materia/actions/qchem.py
materia/dataseries/__init__.py
materia/dataseries/data.py
materia/dataseries/dataseries.py
materia/engines/__init__.py
materia/engines/ccdc.py
materia/engines/engine.py
materia/engines/fragit.py
materia/engines/gamess.py
materia/engines/gpaw.py
materia/engines/multiwfn.py
materia/engines/openbabel.py
materia/engines/packmol.py
materia/engines/qchem.py
materia/engines/vasp.py
materia/engines/xtb.py
materia/handler.py
materia/math.py
materia/molecule/__init__.py
materia/molecule/atom.py
materia/molecule/molecule.py
materia/molecule/structure.py
materia/properties.py
materia/quantity.py
materia/symmetry/__init__.py
materia/symmetry/group_theory.py
materia/symmetry/symfinder.py
materia/symmetry/symmetry_operation.py
materia/tasks.py
materia/units.py
materia/utils.py
materia/workflow.py
materia-10.0.0.dist-info/LICENSE
materia-10.0.0.dist-info/WHEEL
materia-10.0.0.dist-info/METADATA
materia-10.0.0.dist-info/RECORD
